winpwn/__init__.py
winpwn/context.py
winpwn/dbg.py
winpwn/misc.py
winpwn/var.py
winpwn/win.py
winpwn/winpwn.py
ownpwn-0.0.1.dist-info/METADATA
ownpwn-0.0.1.dist-info/WHEEL
ownpwn-0.0.1.dist-info/top_level.txt
ownpwn-0.0.1.dist-info/RECORD
